tagee/TAGEE.py
tagee/__init__.py
tagee-0.3.0.dist-info/METADATA
tagee-0.3.0.dist-info/WHEEL
tagee-0.3.0.dist-info/licenses/LICENSE
tagee-0.3.0.dist-info/RECORD
