Metadata-Version: 2.4
Name: tagee
Version: 0.3.0
Summary: A suite of terrain analysis tools for Google Earth Engine.
Project-URL: Homepage, https://github.com/zecojls/tagee
Project-URL: Issues, https://github.com/zecojls/tagee/issues
Author-email: Jose Lucas <zecojls@gmail.com>
License:                     GNU AFFERO GENERAL PUBLIC LICENSE
License-File: LICENSE
Classifier: Operating System :: OS Independent
Classifier: Programming Language :: Python :: 3
Requires-Python: >=3.8
Requires-Dist: earthengine-api
